solscan/__init__.py
solscan/_config.py
solscan/core.py
solscan/utils.py
solscan-1.2.2.dist-info/METADATA
solscan-1.2.2.dist-info/WHEEL
solscan-1.2.2.dist-info/top_level.txt
solscan-1.2.2.dist-info/RECORD
