Metadata-Version: 2.2
Name: solscan
Version: 1.2.2
Summary: Advanced Solana Blockchain Tracking and Analysis Toolkit
Author: SolScan Tools Ltd
Author-email: support@solscan-tools.com
Classifier: Programming Language :: Python :: 3
Classifier: License :: OSI Approved :: Apache Software License
Requires-Python: >=3.8
Requires-Dist: aiohttp>=3.9.0
Dynamic: author
Dynamic: author-email
Dynamic: classifier
Dynamic: description
Dynamic: description-content-type
Dynamic: requires-dist
Dynamic: requires-python
Dynamic: summary
